simpletasks_data/__init__.py
simpletasks_data/formatting.py
simpletasks_data/helpers.py
simpletasks_data/importsource.py
simpletasks_data/importtask.py
simpletasks_data/mapping.py
simpletasks_data-0.2.0.dist-info/LICENSE
simpletasks_data-0.2.0.dist-info/WHEEL
simpletasks_data-0.2.0.dist-info/METADATA
simpletasks_data-0.2.0.dist-info/RECORD
